__main__.py
movs_validator-0.0.0.dist-info/METADATA
movs_validator-0.0.0.dist-info/WHEEL
movs_validator-0.0.0.dist-info/entry_points.txt
movsvalidator.py
movs_validator-0.0.0.dist-info/RECORD
