Metadata-Version: 2.1
Name: movs-validator
Version: 0.0.0
Project-URL: Homepage, https://github.com/ZeeD/movs-validator
Project-URL: Repository, https://github.com/ZeeD/movs-validator.git
Requires-Python: ==3.12.*
Requires-Dist: movslib>=0.0.0
Requires-Dist: mypy>=1.10.1; extra == "dev"
Requires-Dist: ruff>=0.5.0; extra == "dev"
Provides-Extra: dev
